assemblyline_core/__init__.py
assemblyline_core/server_base.py
assemblyline_core/submission_client.py
assemblyline_core/alerter/__init__.py
assemblyline_core/alerter/processing.py
assemblyline_core/alerter/run_alerter.py
assemblyline_core/dispatching/__init__.py
assemblyline_core/dispatching/client.py
assemblyline_core/dispatching/dispatch_hash.py
assemblyline_core/dispatching/dispatcher.py
assemblyline_core/dispatching/run_files.py
assemblyline_core/dispatching/run_submissions.py
assemblyline_core/expiry/__init__.py
assemblyline_core/expiry/run_expiry.py
assemblyline_core/ingester/__init__.py
assemblyline_core/ingester/constants.py
assemblyline_core/ingester/ingester.py
assemblyline_core/ingester/run_ingest.py
assemblyline_core/ingester/run_internal.py
assemblyline_core/ingester/run_submit.py
assemblyline_core/metrics/__init__.py
assemblyline_core/metrics/es_metrics.py
assemblyline_core/metrics/heartbeat_formatter.py
assemblyline_core/metrics/helper.py
assemblyline_core/metrics/metrics_server.py
assemblyline_core/metrics/run_heartbeat_manager.py
assemblyline_core/metrics/run_metrics_aggregator.py
assemblyline_core/plumber/__init__.py
assemblyline_core/plumber/run_plumber.py
assemblyline_core/scaler/__init__.py
assemblyline_core/scaler/collection.py
assemblyline_core/scaler/run_scaler.py
assemblyline_core/scaler/scaler_server.py
assemblyline_core/scaler/controllers/__init__.py
assemblyline_core/scaler/controllers/docker_ctl.py
assemblyline_core/scaler/controllers/interface.py
assemblyline_core/scaler/controllers/kubernetes_ctl.py
assemblyline_core/updater/__init__.py
assemblyline_core/updater/run_updater.py
assemblyline_core/updater/url_update.py
assemblyline_core/watcher/__init__.py
assemblyline_core/watcher/client.py
assemblyline_core/watcher/run_watcher.py
assemblyline_core/watcher/server.py
assemblyline_core/workflow/__init__.py
assemblyline_core/workflow/run_workflow.py
test/__init__.py
test/conftest.py
test/test_alerter.py
test/test_dispatch_hash.py
assemblyline_core-4.0.0.dev199.dist-info/LICENCE.md
assemblyline_core-4.0.0.dev199.dist-info/METADATA
assemblyline_core-4.0.0.dev199.dist-info/WHEEL
assemblyline_core-4.0.0.dev199.dist-info/top_level.txt
assemblyline_core-4.0.0.dev199.dist-info/RECORD
