Metadata-Version: 2.1
Name: assemblyline-core
Version: 4.0.0.dev199
Summary: Assemblyline (v4) automated malware analysis framework - Core components.
Home-page: https://bitbucket.org/cse-assemblyline/alv4_core/
Author: CCCS Assemblyline development team
Author-email: assemblyline@cyber.gc.ca
License: MIT
Keywords: assemblyline malware gc canada cse-cst cse cst cyber cccs
Platform: UNKNOWN
Classifier: Development Status :: 2 - Pre-Alpha
Classifier: Intended Audience :: Developers
Classifier: Topic :: Software Development :: Libraries
Classifier: License :: OSI Approved :: MIT License
Classifier: Programming Language :: Python :: 3.7
Classifier: Programming Language :: Python :: 3.8
Requires-Dist: urllib3 (<1.25)
Requires-Dist: assemblyline
Requires-Dist: docker
Provides-Extra: test
Requires-Dist: fakeredis[lua] ; extra == 'test'
Requires-Dist: pytest ; extra == 'test'
